FPGA/sinaisXYZ/encoder_demux.v
// ========================================================
// Demultiplexador síncrono (Receptor)
// Reconstrói os sinais X, Y, Z, CTE a partir de Ths e sel
// ========================================================

module demux4_decoder(
    input clk50,
    input [1:0] sel,
    input Ths,
    output reg X_rec = 0,
    output reg Y_rec = 0,
    output reg Z_rec = 0,
    output reg CTE_rec = 0
);

    // Registrador para atrasar o seletor em 1 ciclo de clock
    reg [1:0] sel_d = 0;

    always @(posedge clk50) begin
        // Atraso do seletor para compensar a atualização simultânea no transmissor
        sel_d <= sel;

        // Atualiza apenas o canal correspondente ao seletor atrasado
        case (sel_d)
            2'b00: X_rec  <= Ths;    // Canal X
            2'b01: Y_rec  <= Ths;    // Canal Y
            2'b10: Z_rec  <= Ths;    // Canal Z
            2'b11: CTE_rec <= Ths;   // Canal Constante
        endcase
    end

endmodule

FPGA/sinaisXYZ/encoder_mux.v


// --------------------------------------------------------
// Divisor de clock - base de tempo dos sinais X, Y, Z
// --------------------------------------------------------
module clockDivider1(
    input clki,
    output clko
);
    // 450 m/min: DIV=3141 | 600 m/min: DIV=2356 | teste rápido: DIV=100
    parameter DIV = 100;

    reg [11:0] count = 0;
    reg out = 0;

    always @(posedge clki) begin
        if (count == DIV) begin
            count <= 0;
            out <= ~out;
        end else begin
            count <= count + 1;
        end
    end

    assign clko = out;
endmodule

// --------------------------------------------------------
// Gerador dos canais X e Y (sinais em quadratura)
// --------------------------------------------------------
module genXY(
    input clkTz,
    output X, Y
);
    reg outX = 0, outY = 0;
    reg [1:0] count = 0;

    always @(posedge clkTz)
        count <= count + 1;

    always @(count) begin
        case (count)
            0: begin outX <= 1'b1; outY <= 1'b0; end
            1: begin outX <= 1'b1; outY <= 1'b1; end
            2: begin outX <= 1'b0; outY <= 1'b1; end
            3: begin outX <= 1'b0; outY <= 1'b0; end
        endcase
    end

    assign X = outX;
    assign Y = outY;
endmodule

// --------------------------------------------------------
// Gerador do canal Z (pulso de sincronismo)
// --------------------------------------------------------
module genZ(
    input clkTz,
    output Z
);
    reg [10:0] i = 0;
    reg outZ = 0;

    always @(posedge clkTz) begin
        if (i >= 1999)
            i <= 0;
        else
            i <= i + 1;

        // Pulso de 5 ciclos
        if (i < 5)
            outZ <= 1'b1;
        else
            outZ <= 1'b0;
    end

    assign Z = outZ;
endmodule

// --------------------------------------------------------
// Concentrador MUX
// --------------------------------------------------------
module mux4_encoder(
    input clk50,
    input encX,
    input encY,
    input pulse,
    input cte,
    output reg Ths = 0,
    output reg [1:0] sel = 0
);
    always @(posedge clk50) begin
        

        case (sel)
            2'b00: Ths <= encX;
            2'b01: Ths <= encY;
            2'b10: Ths <= pulse;
            2'b11: Ths <= cte;
            default: Ths <= 1'b0;
        endcase
        sel <= sel + 1;  // Contador 0–3 
    end
endmodule


// --------------------------------------------------------
// Top-level do sistema 
// --------------------------------------------------------
module vincador_top(
    input CLOCK_50,
    output X, Y, Z,
    output Ths,
    output [1:0] sel
);
    wire clkTz;
    wire cte = 1'b1; // constante

    // Clock base
    clockDivider1 #(.DIV(2)) div1 (
        .clki(CLOCK_50),
        .clko(clkTz)
    );

    // Geração dos sinais do encoder
    genXY xygen (.clkTz(clkTz), .X(X), .Y(Y));
    genZ zgen   (.clkTz(clkTz), .Z(Z));

    // MUX síncrono
    mux4_encoder mux (
        .clk50(CLOCK_50),
        .encX(X),
        .encY(Y),
        .pulse(Z),
        .cte(cte),
        .Ths(Ths),
        .sel(sel)
    );
endmodule

FPGA/sinaisXYZ/encoder_demux_tb.v
`include "encoder_mux.v"
`include "encoder_demux.v"
`timescale 1ns/1ps

module encoder_demux_tb;
    reg CLOCK_50 = 0;
    wire X, Y, Z, clkTz, Ths;
    wire [1:0] sel;

    // Sinais reconstituídos
    wire X_rec, Y_rec, Z_rec, CTE_rec;

    // Instancia o transmissor
    vincador_top uut_tx (
        .CLOCK_50(CLOCK_50),
        .X(X),
        .Y(Y),
        .Z(Z),
        .Ths(Ths),
        .sel(sel)
    );

    demux4_decoder uut_rx (
        .clk50(CLOCK_50),
        .sel(sel),
        .Ths(Ths),
        .X_rec(X_rec),
        .Y_rec(Y_rec),
        .Z_rec(Z_rec),
        .CTE_rec(CTE_rec)
    );

    // Clock 50 MHz
    always #10 CLOCK_50 = ~CLOCK_50;

    initial begin
        $dumpfile("encoder_demux.vcd");
        $dumpvars(0, encoder_demux_tb);
        #10000; // tempo total de simulação
        $finish;
    end
endmodule

FPGA/sinaisXYZ/encoder_demux.vcd
$date
	Sun Oct 26 23:38:26 2025
$end
$version
	Icarus Verilog
$end
$timescale
	1ps
$end
$scope module encoder_demux_tb $end
$var wire 2 ! sel [1:0] $end
$var wire 1 " Z_rec $end
$var wire 1 # Z $end
$var wire 1 $ Y_rec $end
$var wire 1 % Y $end
$var wire 1 & X_rec $end
$var wire 1 ' X $end
$var wire 1 ( Ths $end
$var wire 1 ) CTE_rec $end
$var reg 1 * CLOCK_50 $end
$scope module uut_rx $end
$var wire 1 * clk50 $end
$var wire 2 + sel [1:0] $end
$var wire 1 ( Ths $end
$var reg 1 ) CTE_rec $end
$var reg 1 & X_rec $end
$var reg 1 $ Y_rec $end
$var reg 1 " Z_rec $end
$var reg 2 , sel_d [1:0] $end
$upscope $end
$scope module uut_tx $end
$var wire 1 * CLOCK_50 $end
$var wire 1 - cte $end
$var wire 2 . sel [1:0] $end
$var wire 1 / clkTz $end
$var wire 1 # Z $end
$var wire 1 % Y $end
$var wire 1 ' X $end
$var wire 1 ( Ths $end
$scope module div1 $end
$var wire 1 * clki $end
$var wire 1 / clko $end
$var parameter 32 0 DIV $end
$var reg 12 1 count [11:0] $end
$var reg 1 2 out $end
$upscope $end
$scope module mux $end
$var wire 1 * clk50 $end
$var wire 1 - cte $end
$var wire 1 # pulse $end
$var wire 1 % encY $end
$var wire 1 ' encX $end
$var reg 1 ( Ths $end
$var reg 2 3 sel [1:0] $end
$upscope $end
$scope module xygen $end
$var wire 1 ' X $end
$var wire 1 % Y $end
$var wire 1 / clkTz $end
$var reg 2 4 count [1:0] $end
$var reg 1 5 outX $end
$var reg 1 6 outY $end
$upscope $end
$scope module zgen $end
$var wire 1 # Z $end
$var wire 1 / clkTz $end
$var reg 11 7 i [10:0] $end
$var reg 1 8 outZ $end
$upscope $end
$upscope $end
$upscope $end
$enddefinitions $end
$comment Show the parameter values. $end
$dumpall
b10 0
$end
#0
$dumpvars
08
b0 7
06
15
b0 4
b0 3
02
b0 1
0/
b0 .
1-
b0 ,
b0 +
0*
0)
0(
1'
0&
0%
0$
0#
0"
b0 !
$end
#10000
b1 1
b1 !
b1 +
b1 .
b1 3
1(
1*
#20000
0*
#30000
1&
b1 ,
b10 !
b10 +
b10 .
b10 3
0(
b10 1
1*
#40000
0*
#50000
1%
16
b1 4
1#
18
b1 7
1/
12
b0 1
b11 !
b11 +
b11 .
b11 3
b10 ,
1*
#60000
0*
#70000
b11 ,
b0 !
b0 +
b0 .
b0 3
1(
b1 1
1*
#80000
0*
#90000
b10 1
b1 !
b1 +
b1 .
b1 3
1)
b0 ,
1*
#100000
0*
#110000
b1 ,
b10 !
b10 +
b10 .
b10 3
0/
02
b0 1
1*
#120000
0*
#130000
b1 1
b11 !
b11 +
b11 .
b11 3
1$
b10 ,
1*
#140000
0*
#150000
1"
b11 ,
b0 !
b0 +
b0 .
b0 3
b10 1
1*
#160000
0*
#170000
0'
05
b10 7
b10 4
1/
12
b0 1
b1 !
b1 +
b1 .
b1 3
b0 ,
1*
#180000
0*
#190000
b1 ,
b10 !
b10 +
b10 .
b10 3
b1 1
1*
#200000
0*
#210000
b10 1
b11 !
b11 +
b11 .
b11 3
b10 ,
1*
#220000
0*
#230000
b11 ,
b0 !
b0 +
b0 .
b0 3
0/
02
b0 1
1*
#240000
0*
#250000
b1 1
b1 !
b1 +
b1 .
b1 3
0(
b0 ,
1*
#260000
0*
#270000
0&
b1 ,
b10 !
b10 +
b10 .
b10 3
1(
b10 1
1*
#280000
0*
#290000
0%
06
b11 4
b11 7
1/
12
b0 1
b11 !
b11 +
b11 .
b11 3
b10 ,
1*
#300000
0*
#310000
b11 ,
b0 !
b0 +
b0 .
b0 3
b1 1
1*
#320000
0*
#330000
b10 1
b1 !
b1 +
b1 .
b1 3
0(
b0 ,
1*
#340000
0*
#350000
b1 ,
b10 !
b10 +
b10 .
b10 3
0/
02
b0 1
1*
#360000
0*
#370000
b1 1
b11 !
b11 +
b11 .
b11 3
1(
0$
b10 ,
1*
#380000
0*
#390000
b11 ,
b0 !
b0 +
b0 .
b0 3
b10 1
1*
#400000
0*
#410000
1'
15
b100 7
b0 4
1/
12
b0 1
b1 !
b1 +
b1 .
b1 3
0(
b0 ,
1*
#420000
0*
#430000
b1 ,
b10 !
b10 +
b10 .
b10 3
b1 1
1*
#440000
0*
#450000
b10 1
b11 !
b11 +
b11 .
b11 3
1(
b10 ,
1*
#460000
0*
#470000
b11 ,
b0 !
b0 +
b0 .
b0 3
0/
02
b0 1
1*
#480000
0*
#490000
b1 1
b1 !
b1 +
b1 .
b1 3
b0 ,
1*
#500000
0*
#510000
1&
b1 ,
b10 !
b10 +
b10 .
b10 3
0(
b10 1
1*
#520000
0*
#530000
1%
16
b1 4
b101 7
1/
12
b0 1
b11 !
b11 +
b11 .
b11 3
1(
b10 ,
1*
#540000
0*
#550000
b11 ,
b0 !
b0 +
b0 .
b0 3
b1 1
1*
#560000
0*
#570000
b10 1
b1 !
b1 +
b1 .
b1 3
b0 ,
1*
#580000
0*
#590000
b1 ,
b10 !
b10 +
b10 .
b10 3
0/
02
b0 1
1*
#600000
0*
#610000
b1 1
b11 !
b11 +
b11 .
b11 3
1$
b10 ,
1*
#620000
0*
#630000
b11 ,
b0 !
b0 +
b0 .
b0 3
b10 1
1*
#640000
0*
#650000
0'
05
0#
08
b110 7
b10 4
1/
12
b0 1
b1 !
b1 +
b1 .
b1 3
b0 ,
1*
#660000
0*
#670000
b1 ,
b10 !
b10 +
b10 .
b10 3
b1 1
1*
#680000
0*
#690000
b10 1
b11 !
b11 +
b11 .
b11 3
0(
b10 ,
1*
#700000
0*
#710000
0"
b11 ,
b0 !
b0 +
b0 .
b0 3
1(
0/
02
b0 1
1*
#720000
0*
#730000
b1 1
b1 !
b1 +
b1 .
b1 3
0(
b0 ,
1*
#740000
0*
#750000
0&
b1 ,
b10 !
b10 +
b10 .
b10 3
1(
b10 1
1*
#760000
0*
#770000
0%
06
b11 4
b111 7
1/
12
b0 1
b11 !
b11 +
b11 .
b11 3
0(
b10 ,
1*
#780000
0*
#790000
b11 ,
b0 !
b0 +
b0 .
b0 3
1(
b1 1
1*
#800000
0*
#810000
b10 1
b1 !
b1 +
b1 .
b1 3
0(
b0 ,
1*
#820000
0*
#830000
b1 ,
b10 !
b10 +
b10 .
b10 3
0/
02
b0 1
1*
#840000
0*
#850000
b1 1
b11 !
b11 +
b11 .
b11 3
0$
b10 ,
1*
#860000
0*
#870000
b11 ,
b0 !
b0 +
b0 .
b0 3
1(
b10 1
1*
#880000
0*
#890000
1'
15
b1000 7
b0 4
1/
12
b0 1
b1 !
b1 +
b1 .
b1 3
0(
b0 ,
1*
#900000
0*
#910000
b1 ,
b10 !
b10 +
b10 .
b10 3
b1 1
1*
#920000
0*
#930000
b10 1
b11 !
b11 +
b11 .
b11 3
b10 ,
1*
#940000
0*
#950000
b11 ,
b0 !
b0 +
b0 .
b0 3
1(
0/
02
b0 1
1*
#960000
0*
#970000
b1 1
b1 !
b1 +
b1 .
b1 3
b0 ,
1*
#980000
0*
#990000
1&
b1 ,
b10 !
b10 +
b10 .
b10 3
0(
b10 1
1*
#1000000
0*
#1010000
1%
16
b1 4
b1001 7
1/
12
b0 1
b11 !
b11 +
b11 .
b11 3
b10 ,
1*
#1020000
0*
#1030000
b11 ,
b0 !
b0 +
b0 .
b0 3
1(
b1 1
1*
#1040000
0*
#1050000
b10 1
b1 !
b1 +
b1 .
b1 3
b0 ,
1*
#1060000
0*
#1070000
b1 ,
b10 !
b10 +
b10 .
b10 3
0/
02
b0 1
1*
#1080000
0*
#1090000
b1 1
b11 !
b11 +
b11 .
b11 3
0(
1$
b10 ,
1*
#1100000
0*
#1110000
b11 ,
b0 !
b0 +
b0 .
b0 3
1(
b10 1
1*
#1120000
0*
#1130000
0'
05
b1010 7
b10 4
1/
12
b0 1
b1 !
b1 +
b1 .
b1 3
b0 ,
1*
#1140000
0*
#1150000
b1 ,
b10 !
b10 +
b10 .
b10 3
b1 1
1*
#1160000
0*
#1170000
b10 1
b11 !
b11 +
b11 .
b11 3
0(
b10 ,
1*
#1180000
0*
#1190000
b11 ,
b0 !
b0 +
b0 .
b0 3
1(
0/
02
b0 1
1*
#1200000
0*
#1210000
b1 1
b1 !
b1 +
b1 .
b1 3
0(
b0 ,
1*
#1220000
0*
#1230000
0&
b1 ,
b10 !
b10 +
b10 .
b10 3
1(
b10 1
1*
#1240000
0*
#1250000
0%
06
b11 4
b1011 7
1/
12
b0 1
b11 !
b11 +
b11 .
b11 3
0(
b10 ,
1*
#1260000
0*
#1270000
b11 ,
b0 !
b0 +
b0 .
b0 3
1(
b1 1
1*
#1280000
0*
#1290000
b10 1
b1 !
b1 +
b1 .
b1 3
0(
b0 ,
1*
#1300000
0*
#1310000
b1 ,
b10 !
b10 +
b10 .
b10 3
0/
02
b0 1
1*
#1320000
0*
#1330000
b1 1
b11 !
b11 +
b11 .
b11 3
0$
b10 ,
1*
#1340000
0*
#1350000
b11 ,
b0 !
b0 +
b0 .
b0 3
1(
b10 1
1*
#1360000
0*
#1370000
1'
15
b1100 7
b0 4
1/
12
b0 1
b1 !
b1 +
b1 .
b1 3
0(
b0 ,
1*
#1380000
0*
#1390000
b1 ,
b10 !
b10 +
b10 .
b10 3
b1 1
1*
#1400000
0*
#1410000
b10 1
b11 !
b11 +
b11 .
b11 3
b10 ,
1*
#1420000
0*
#1430000
b11 ,
b0 !
b0 +
b0 .
b0 3
1(
0/
02
b0 1
1*
#1440000
0*
#1450000
b1 1
b1 !
b1 +
b1 .
b1 3
b0 ,
1*
#1460000
0*
#1470000
1&
b1 ,
b10 !
b10 +
b10 .
b10 3
0(
b10 1
1*
#1480000
0*
#1490000
1%
16
b1 4
b1101 7
1/
12
b0 1
b11 !
b11 +
b11 .
b11 3
b10 ,
1*
#1500000
0*
#1510000
b11 ,
b0 !
b0 +
b0 .
b0 3
1(
b1 1
1*
#1520000
0*
#1530000
b10 1
b1 !
b1 +
b1 .
b1 3
b0 ,
1*
#1540000
0*
#1550000
b1 ,
b10 !
b10 +
b10 .
b10 3
0/
02
b0 1
1*
#1560000
0*
#1570000
b1 1
b11 !
b11 +
b11 .
b11 3
0(
1$
b10 ,
1*
#1580000
0*
#1590000
b11 ,
b0 !
b0 +
b0 .
b0 3
1(
b10 1
1*
#1600000
0*
#1610000
0'
05
b1110 7
b10 4
1/
12
b0 1
b1 !
b1 +
b1 .
b1 3
b0 ,
1*
#1620000
0*
#1630000
b1 ,
b10 !
b10 +
b10 .
b10 3
b1 1
1*
#1640000
0*
#1650000
b10 1
b11 !
b11 +
b11 .
b11 3
0(
b10 ,
1*
#1660000
0*
#1670000
b11 ,
b0 !
b0 +
b0 .
b0 3
1(
0/
02
b0 1
1*
#1680000
0*
#1690000
b1 1
b1 !
b1 +
b1 .
b1 3
0(
b0 ,
1*
#1700000
0*
#1710000
0&
b1 ,
b10 !
b10 +
b10 .
b10 3
1(
b10 1
1*
#1720000
0*
#1730000
0%
06
b11 4
b1111 7
1/
12
b0 1
b11 !
b11 +
b11 .
b11 3
0(
b10 ,
1*
#1740000
0*
#1750000
b11 ,
b0 !
b0 +
b0 .
b0 3
1(
b1 1
1*
#1760000
0*
#1770000
b10 1
b1 !
b1 +
b1 .
b1 3
0(
b0 ,
1*
#1780000
0*
#1790000
b1 ,
b10 !
b10 +
b10 .
b10 3
0/
02
b0 1
1*
#1800000
0*
#1810000
b1 1
b11 !
b11 +
b11 .
b11 3
0$
b10 ,
1*
#1820000
0*
#1830000
b11 ,
b0 !
b0 +
b0 .
b0 3
1(
b10 1
1*
#1840000
0*
#1850000
1'
15
b10000 7
b0 4
1/
12
b0 1
b1 !
b1 +
b1 .
b1 3
0(
b0 ,
1*
#1860000
0*
#1870000
b1 ,
b10 !
b10 +
b10 .
b10 3
b1 1
1*
#1880000
0*
#1890000
b10 1
b11 !
b11 +
b11 .
b11 3
b10 ,
1*
#1900000
0*
#1910000
b11 ,
b0 !
b0 +
b0 .
b0 3
1(
0/
02
b0 1
1*
#1920000
0*
#1930000
b1 1
b1 !
b1 +
b1 .
b1 3
b0 ,
1*
#1940000
0*
#1950000
1&
b1 ,
b10 !
b10 +
b10 .
b10 3
0(
b10 1
1*
#1960000
0*
#1970000
1%
16
b1 4
b10001 7
1/
12
b0 1
b11 !
b11 +
b11 .
b11 3
b10 ,
1*
#1980000
0*
#1990000
b11 ,
b0 !
b0 +
b0 .
b0 3
1(
b1 1
1*
#2000000
0*
#2010000
b10 1
b1 !
b1 +
b1 .
b1 3
b0 ,
1*
#2020000
0*
#2030000
b1 ,
b10 !
b10 +
b10 .
b10 3
0/
02
b0 1
1*
#2040000
0*
#2050000
b1 1
b11 !
b11 +
b11 .
b11 3
0(
1$
b10 ,
1*
#2060000
0*
#2070000
b11 ,
b0 !
b0 +
b0 .
b0 3
1(
b10 1
1*
#2080000
0*
#2090000
0'
05
b10010 7
b10 4
1/
12
b0 1
b1 !
b1 +
b1 .
b1 3
b0 ,
1*
#2100000
0*
#2110000
b1 ,
b10 !
b10 +
b10 .
b10 3
b1 1
1*
#2120000
0*
#2130000
b10 1
b11 !
b11 +
b11 .
b11 3
0(
b10 ,
1*
#2140000
0*
#2150000
b11 ,
b0 !
b0 +
b0 .
b0 3
1(
0/
02
b0 1
1*
#2160000
0*
#2170000
b1 1
b1 !
b1 +
b1 .
b1 3
0(
b0 ,
1*
#2180000
0*
#2190000
0&
b1 ,
b10 !
b10 +
b10 .
b10 3
1(
b10 1
1*
#2200000
0*
#2210000
0%
06
b11 4
b10011 7
1/
12
b0 1
b11 !
b11 +
b11 .
b11 3
0(
b10 ,
1*
#2220000
0*
#2230000
b11 ,
b0 !
b0 +
b0 .
b0 3
1(
b1 1
1*
#2240000
0*
#2250000
b10 1
b1 !
b1 +
b1 .
b1 3
0(
b0 ,
1*
#2260000
0*
#2270000
b1 ,
b10 !
b10 +
b10 .
b10 3
0/
02
b0 1
1*
#2280000
0*
#2290000
b1 1
b11 !
b11 +
b11 .
b11 3
0$
b10 ,
1*
#2300000
0*
#2310000
b11 ,
b0 !
b0 +
b0 .
b0 3
1(
b10 1
1*
#2320000
0*
#2330000
1'
15
b10100 7
b0 4
1/
12
b0 1
b1 !
b1 +
b1 .
b1 3
0(
b0 ,
1*
#2340000
0*
#2350000
b1 ,
b10 !
b10 +
b10 .
b10 3
b1 1
1*
#2360000
0*
#2370000
b10 1
b11 !
b11 +
b11 .
b11 3
b10 ,
1*
#2380000
0*
#2390000
b11 ,
b0 !
b0 +
b0 .
b0 3
1(
0/
02
b0 1
1*
#2400000
0*
#2410000
b1 1
b1 !
b1 +
b1 .
b1 3
b0 ,
1*
#2420000
0*
#2430000
1&
b1 ,
b10 !
b10 +
b10 .
b10 3
0(
b10 1
1*
#2440000
0*
#2450000
1%
16
b1 4
b10101 7
1/
12
b0 1
b11 !
b11 +
b11 .
b11 3
b10 ,
1*
#2460000
0*
#2470000
b11 ,
b0 !
b0 +
b0 .
b0 3
1(
b1 1
1*
#2480000
0*
#2490000
b10 1
b1 !
b1 +
b1 .
b1 3
b0 ,
1*
#2500000
0*
#2510000
b1 ,
b10 !
b10 +
b10 .
b10 3
0/
02
b0 1
1*
#2520000
0*
#2530000
b1 1
b11 !
b11 +
b11 .
b11 3
0(
1$
b10 ,
1*
#2540000
0*
#2550000
b11 ,
b0 !
b0 +
b0 .
b0 3
1(
b10 1
1*
#2560000
0*
#2570000
0'
05
b10110 7
b10 4
1/
12
b0 1
b1 !
b1 +
b1 .
b1 3
b0 ,
1*
#2580000
0*
#2590000
b1 ,
b10 !
b10 +
b10 .
b10 3
b1 1
1*
#2600000
0*
#2610000
b10 1
b11 !
b11 +
b11 .
b11 3
0(
b10 ,
1*
#2620000
0*
#2630000
b11 ,
b0 !
b0 +
b0 .
b0 3
1(
0/
02
b0 1
1*
#2640000
0*
#2650000
b1 1
b1 !
b1 +
b1 .
b1 3
0(
b0 ,
1*
#2660000
0*
#2670000
0&
b1 ,
b10 !
b10 +
b10 .
b10 3
1(
b10 1
1*
#2680000
0*
#2690000
0%
06
b11 4
b10111 7
1/
12
b0 1
b11 !
b11 +
b11 .
b11 3
0(
b10 ,
1*
#2700000
0*
#2710000
b11 ,
b0 !
b0 +
b0 .
b0 3
1(
b1 1
1*
#2720000
0*
#2730000
b10 1
b1 !
b1 +
b1 .
b1 3
0(
b0 ,
1*
#2740000
0*
#2750000
b1 ,
b10 !
b10 +
b10 .
b10 3
0/
02
b0 1
1*
#2760000
0*
#2770000
b1 1
b11 !
b11 +
b11 .
b11 3
0$
b10 ,
1*
#2780000
0*
#2790000
b11 ,
b0 !
b0 +
b0 .
b0 3
1(
b10 1
1*
#2800000
0*
#2810000
1'
15
b11000 7
b0 4
1/
12
b0 1
b1 !
b1 +
b1 .
b1 3
0(
b0 ,
1*
#2820000
0*
#2830000
b1 ,
b10 !
b10 +
b10 .
b10 3
b1 1
1*
#2840000
0*
#2850000
b10 1
b11 !
b11 +
b11 .
b11 3
b10 ,
1*
#2860000
0*
#2870000
b11 ,
b0 !
b0 +
b0 .
b0 3
1(
0/
02
b0 1
1*
#2880000
0*
#2890000
b1 1
b1 !
b1 +
b1 .
b1 3
b0 ,
1*
#2900000
0*
#2910000
1&
b1 ,
b10 !
b10 +
b10 .
b10 3
0(
b10 1
1*
#2920000
0*
#2930000
1%
16
b1 4
b11001 7
1/
12
b0 1
b11 !
b11 +
b11 .
b11 3
b10 ,
1*
#2940000
0*
#2950000
b11 ,
b0 !
b0 +
b0 .
b0 3
1(
b1 1
1*
#2960000
0*
#2970000
b10 1
b1 !
b1 +
b1 .
b1 3
b0 ,
1*
#2980000
0*
#2990000
b1 ,
b10 !
b10 +
b10 .
b10 3
0/
02
b0 1
1*
#3000000
0*
#3010000
b1 1
b11 !
b11 +
b11 .
b11 3
0(
1$
b10 ,
1*
#3020000
0*
#3030000
b11 ,
b0 !
b0 +
b0 .
b0 3
1(
b10 1
1*
#3040000
0*
#3050000
0'
05
b11010 7
b10 4
1/
12
b0 1
b1 !
b1 +
b1 .
b1 3
b0 ,
1*
#3060000
0*
#3070000
b1 ,
b10 !
b10 +
b10 .
b10 3
b1 1
1*
#3080000
0*
#3090000
b10 1
b11 !
b11 +
b11 .
b11 3
0(
b10 ,
1*
#3100000
0*
#3110000
b11 ,
b0 !
b0 +
b0 .
b0 3
1(
0/
02
b0 1
1*
#3120000
0*
#3130000
b1 1
b1 !
b1 +
b1 .
b1 3
0(
b0 ,
1*
#3140000
0*
#3150000
0&
b1 ,
b10 !
b10 +
b10 .
b10 3
1(
b10 1
1*
#3160000
0*
#3170000
0%
06
b11 4
b11011 7
1/
12
b0 1
b11 !
b11 +
b11 .
b11 3
0(
b10 ,
1*
#3180000
0*
#3190000
b11 ,
b0 !
b0 +
b0 .
b0 3
1(
b1 1
1*
#3200000
0*
#3210000
b10 1
b1 !
b1 +
b1 .
b1 3
0(
b0 ,
1*
#3220000
0*
#3230000
b1 ,
b10 !
b10 +
b10 .
b10 3
0/
02
b0 1
1*
#3240000
0*
#3250000
b1 1
b11 !
b11 +
b11 .
b11 3
0$
b10 ,
1*
#3260000
0*
#3270000
b11 ,
b0 !
b0 +
b0 .
b0 3
1(
b10 1
1*
#3280000
0*
#3290000
1'
15
b11100 7
b0 4
1/
12
b0 1
b1 !
b1 +
b1 .
b1 3
0(
b0 ,
1*
#3300000
0*
#3310000
b1 ,
b10 !
b10 +
b10 .
b10 3
b1 1
1*
#3320000
0*
#3330000
b10 1
b11 !
b11 +
b11 .
b11 3
b10 ,
1*
#3340000
0*
#3350000
b11 ,
b0 !
b0 +
b0 .
b0 3
1(
0/
02
b0 1
1*
#3360000
0*
#3370000
b1 1
b1 !
b1 +
b1 .
b1 3
b0 ,
1*
#3380000
0*
#3390000
1&
b1 ,
b10 !
b10 +
b10 .
b10 3
0(
b10 1
1*
#3400000
0*
#3410000
1%
16
b1 4
b11101 7
1/
12
b0 1
b11 !
b11 +
b11 .
b11 3
b10 ,
1*
#3420000
0*
#3430000
b11 ,
b0 !
b0 +
b0 .
b0 3
1(
b1 1
1*
#3440000
0*
#3450000
b10 1
b1 !
b1 +
b1 .
b1 3
b0 ,
1*
#3460000
0*
#3470000
b1 ,
b10 !
b10 +
b10 .
b10 3
0/
02
b0 1
1*
#3480000
0*
#3490000
b1 1
b11 !
b11 +
b11 .
b11 3
0(
1$
b10 ,
1*
#3500000
0*
#3510000
b11 ,
b0 !
b0 +
b0 .
b0 3
1(
b10 1
1*
#3520000
0*
#3530000
0'
05
b11110 7
b10 4
1/
12
b0 1
b1 !
b1 +
b1 .
b1 3
b0 ,
1*
#3540000
0*
#3550000
b1 ,
b10 !
b10 +
b10 .
b10 3
b1 1
1*
#3560000
0*
#3570000
b10 1
b11 !
b11 +
b11 .
b11 3
0(
b10 ,
1*
#3580000
0*
#3590000
b11 ,
b0 !
b0 +
b0 .
b0 3
1(
0/
02
b0 1
1*
#3600000
0*
#3610000
b1 1
b1 !
b1 +
b1 .
b1 3
0(
b0 ,
1*
#3620000
0*
#3630000
0&
b1 ,
b10 !
b10 +
b10 .
b10 3
1(
b10 1
1*
#3640000
0*
#3650000
0%
06
b11 4
b11111 7
1/
12
b0 1
b11 !
b11 +
b11 .
b11 3
0(
b10 ,
1*
#3660000
0*
#3670000
b11 ,
b0 !
b0 +
b0 .
b0 3
1(
b1 1
1*
#3680000
0*
#3690000
b10 1
b1 !
b1 +
b1 .
b1 3
0(
b0 ,
1*
#3700000
0*
#3710000
b1 ,
b10 !
b10 +
b10 .
b10 3
0/
02
b0 1
1*
#3720000
0*
#3730000
b1 1
b11 !
b11 +
b11 .
b11 3
0$
b10 ,
1*
#3740000
0*
#3750000
b11 ,
b0 !
b0 +
b0 .
b0 3
1(
b10 1
1*
#3760000
0*
#3770000
1'
15
b100000 7
b0 4
1/
12
b0 1
b1 !
b1 +
b1 .
b1 3
0(
b0 ,
1*
#3780000
0*
#3790000
b1 ,
b10 !
b10 +
b10 .
b10 3
b1 1
1*
#3800000
0*
#3810000
b10 1
b11 !
b11 +
b11 .
b11 3
b10 ,
1*
#3820000
0*
#3830000
b11 ,
b0 !
b0 +
b0 .
b0 3
1(
0/
02
b0 1
1*
#3840000
0*
#3850000
b1 1
b1 !
b1 +
b1 .
b1 3
b0 ,
1*
#3860000
0*
#3870000
1&
b1 ,
b10 !
b10 +
b10 .
b10 3
0(
b10 1
1*
#3880000
0*
#3890000
1%
16
b1 4
b100001 7
1/
12
b0 1
b11 !
b11 +
b11 .
b11 3
b10 ,
1*
#3900000
0*
#3910000
b11 ,
b0 !
b0 +
b0 .
b0 3
1(
b1 1
1*
#3920000
0*
#3930000
b10 1
b1 !
b1 +
b1 .
b1 3
b0 ,
1*
#3940000
0*
#3950000
b1 ,
b10 !
b10 +
b10 .
b10 3
0/
02
b0 1
1*
#3960000
0*
#3970000
b1 1
b11 !
b11 +
b11 .
b11 3
0(
1$
b10 ,
1*
#3980000
0*
#3990000
b11 ,
b0 !
b0 +
b0 .
b0 3
1(
b10 1
1*
#4000000
0*
#4010000
0'
05
b100010 7
b10 4
1/
12
b0 1
b1 !
b1 +
b1 .
b1 3
b0 ,
1*
#4020000
0*
#4030000
b1 ,
b10 !
b10 +
b10 .
b10 3
b1 1
1*
#4040000
0*
#4050000
b10 1
b11 !
b11 +
b11 .
b11 3
0(
b10 ,
1*
#4060000
0*
#4070000
b11 ,
b0 !
b0 +
b0 .
b0 3
1(
0/
02
b0 1
1*
#4080000
0*
#4090000
b1 1
b1 !
b1 +
b1 .
b1 3
0(
b0 ,
1*
#4100000
0*
#4110000
0&
b1 ,
b10 !
b10 +
b10 .
b10 3
1(
b10 1
1*
#4120000
0*
#4130000
0%
06
b11 4
b100011 7
1/
12
b0 1
b11 !
b11 +
b11 .
b11 3
0(
b10 ,
1*
#4140000
0*
#4150000
b11 ,
b0 !
b0 +
b0 .
b0 3
1(
b1 1
1*
#4160000
0*
#4170000
b10 1
b1 !
b1 +
b1 .
b1 3
0(
b0 ,
1*
#4180000
0*
#4190000
b1 ,
b10 !
b10 +
b10 .
b10 3
0/
02
b0 1
1*
#4200000
0*
#4210000
b1 1
b11 !
b11 +
b11 .
b11 3
0$
b10 ,
1*
#4220000
0*
#4230000
b11 ,
b0 !
b0 +
b0 .
b0 3
1(
b10 1
1*
#4240000
0*
#4250000
1'
15
b100100 7
b0 4
1/
12
b0 1
b1 !
b1 +
b1 .
b1 3
0(
b0 ,
1*
#4260000
0*
#4270000
b1 ,
b10 !
b10 +
b10 .
b10 3
b1 1
1*
#4280000
0*
#4290000
b10 1
b11 !
b11 +
b11 .
b11 3
b10 ,
1*
#4300000
0*
#4310000
b11 ,
b0 !
b0 +
b0 .
b0 3
1(
0/
02
b0 1
1*
#4320000
0*
#4330000
b1 1
b1 !
b1 +
b1 .
b1 3
b0 ,
1*
#4340000
0*
#4350000
1&
b1 ,
b10 !
b10 +
b10 .
b10 3
0(
b10 1
1*
#4360000
0*
#4370000
1%
16
b1 4
b100101 7
1/
12
b0 1
b11 !
b11 +
b11 .
b11 3
b10 ,
1*
#4380000
0*
#4390000
b11 ,
b0 !
b0 +
b0 .
b0 3
1(
b1 1
1*
#4400000
0*
