FPGA/sinaisXYZ/encoder_mux.v


// --------------------------------------------------------
// Divisor de clock - base de tempo dos sinais X, Y, Z
// --------------------------------------------------------
module clockDivider1(
    input clki,
    output clko
);
    // 450 m/min: DIV=3141 | 600 m/min: DIV=2356 | teste rápido: DIV=100
    parameter DIV = 100;

    reg [11:0] count = 0;
    reg out = 0;

    always @(posedge clki) begin
        if (count == DIV) begin
            count <= 0;
            out <= ~out;
        end else begin
            count <= count + 1;
        end
    end

    assign clko = out;
endmodule

// --------------------------------------------------------
// Gerador dos canais X e Y (sinais em quadratura)
// --------------------------------------------------------
module genXY(
    input clkTz,
    output X, Y
);
    reg outX = 0, outY = 0;
    reg [1:0] count = 0;

    always @(posedge clkTz)
        count <= count + 1;

    always @(count) begin
        case (count)
            0: begin outX <= 1'b1; outY <= 1'b0; end
            1: begin outX <= 1'b1; outY <= 1'b1; end
            2: begin outX <= 1'b0; outY <= 1'b1; end
            3: begin outX <= 1'b0; outY <= 1'b0; end
        endcase
    end

    assign X = outX;
    assign Y = outY;
endmodule

// --------------------------------------------------------
// Gerador do canal Z (pulso de sincronismo)
// --------------------------------------------------------
module genZ(
    input clkTz,
    output Z
);
    reg [10:0] i = 0;
    reg outZ = 0;

    always @(posedge clkTz) begin
        if (i >= 1999)
            i <= 0;
        else
            i <= i + 1;

        // Pulso de 5 ciclos
        if (i < 5)
            outZ <= 1'b1;
        else
            outZ <= 1'b0;
    end

    assign Z = outZ;
endmodule

// --------------------------------------------------------
// Concentrador MUX
// --------------------------------------------------------
module mux4_encoder(
    input clk50,
    input encX,
    input encY,
    input pulse,
    input cte,
    output reg Ths = 0,
    output reg [1:0] sel = 0
);
    always @(posedge clk50) begin
        sel <= sel + 1;  // Contador 0–3 

        case (sel)
            2'b00: Ths <= encX;
            2'b01: Ths <= encY;
            2'b10: Ths <= pulse;
            2'b11: Ths <= cte;
            default: Ths <= 1'b0;
        endcase
    end
endmodule


// --------------------------------------------------------
// Top-level do sistema 
// --------------------------------------------------------
module vincador_top(
    input CLOCK_50,
    output X, Y, Z,
    output Ths,
    output [1:0] sel
);
    wire clkTz;
    wire cte = 1'b1; // constante

    // Clock base
    clockDivider1 #(.DIV(2)) div1 (
        .clki(CLOCK_50),
        .clko(clkTz)
    );

    // Geração dos sinais do encoder
    genXY xygen (.clkTz(clkTz), .X(X), .Y(Y));
    genZ zgen   (.clkTz(clkTz), .Z(Z));

    // MUX síncrono
    mux4_encoder mux (
        .clk50(CLOCK_50),
        .encX(X),
        .encY(Y),
        .pulse(Z),
        .cte(cte),
        .Ths(Ths),
        .sel(sel)
    );
endmodule

FPGA/sinaisXYZ/encoder_mux_tb.v
`include "encoder_mux.v"
`timescale 1ns/100ps

module encoder_mux_tb;
    reg CLOCK_50 = 0;
    wire X, Y, Z, Ths;
    wire [1:0] sel;

    // Instancia o módulo principal
    vincador_top uut (
        .CLOCK_50(CLOCK_50),
        .X(X),
        .Y(Y),
        .Z(Z),
        .Ths(Ths),
        .sel(sel)
    );

    // Clock de 50 MHz → período 20 ns
    always #500 CLOCK_50 = ~CLOCK_50;

    // Simulação
    initial begin
        $dumpfile("encoder_mux.vcd");
        $dumpvars(0, encoder_mux_tb);
        #50000;  // tempo total de simulação (ajuste conforme o zoom desejado)
        $finish;
    end
endmodule

FPGA/sinaisXYZ/encoder_mux.vcd
$date
	Sun Oct 26 19:10:55 2025
$end
$version
	Icarus Verilog
$end
$timescale
	100ps
$end
$scope module encoder_mux_tb $end
$var wire 2 ! sel [1:0] $end
$var wire 1 " Z $end
$var wire 1 # Y $end
$var wire 1 $ X $end
$var wire 1 % Ths $end
$var reg 1 & CLOCK_50 $end
$scope module uut $end
$var wire 1 & CLOCK_50 $end
$var wire 1 ' cte $end
$var wire 2 ( sel [1:0] $end
$var wire 1 ) clkTz $end
$var wire 1 " Z $end
$var wire 1 # Y $end
$var wire 1 $ X $end
$var wire 1 % Ths $end
$scope module div1 $end
$var wire 1 & clki $end
$var wire 1 ) clko $end
$var parameter 32 * DIV $end
$var reg 12 + count [11:0] $end
$var reg 1 , out $end
$upscope $end
$scope module mux $end
$var wire 1 & clk50 $end
$var wire 1 ' cte $end
$var wire 1 " pulse $end
$var wire 1 # encY $end
$var wire 1 $ encX $end
$var reg 1 % Ths $end
$var reg 2 - sel [1:0] $end
$upscope $end
$scope module xygen $end
$var wire 1 $ X $end
$var wire 1 # Y $end
$var wire 1 ) clkTz $end
$var reg 2 . count [1:0] $end
$var reg 1 / outX $end
$var reg 1 0 outY $end
$upscope $end
$scope module zgen $end
$var wire 1 " Z $end
$var wire 1 ) clkTz $end
$var reg 11 1 i [10:0] $end
$var reg 1 2 outZ $end
$upscope $end
$upscope $end
$upscope $end
$enddefinitions $end
$comment Show the parameter values. $end
$dumpall
b10 *
$end
#0
$dumpvars
02
b0 1
00
1/
b0 .
b0 -
0,
b0 +
0)
b0 (
1'
0&
0%
1$
0#
0"
b0 !
$end
#5000
b1 +
1%
b1 !
b1 (
b1 -
1&
#10000
0&
#15000
0%
b10 !
b10 (
b10 -
b10 +
1&
#20000
0&
#25000
1#
10
b1 .
1"
12
b1 1
1)
1,
b0 +
b11 !
b11 (
b11 -
1&
#30000
0&
#35000
1%
b0 !
b0 (
b0 -
b1 +
1&
#40000
0&
#45000
b10 +
b1 !
b1 (
b1 -
1&
#50000
0&
#55000
b10 !
b10 (
b10 -
0)
0,
b0 +
1&
#60000
0&
#65000
b1 +
b11 !
b11 (
b11 -
1&
#70000
0&
#75000
b0 !
b0 (
b0 -
b10 +
1&
#80000
0&
#85000
0$
0/
b10 1
b10 .
1)
1,
b0 +
b1 !
b1 (
b1 -
1&
#90000
0&
#95000
b10 !
b10 (
b10 -
b1 +
1&
#100000
0&
#105000
b10 +
b11 !
b11 (
b11 -
1&
#110000
0&
#115000
b0 !
b0 (
b0 -
0)
0,
b0 +
1&
#120000
0&
#125000
b1 +
0%
b1 !
b1 (
b1 -
1&
#130000
0&
#135000
1%
b10 !
b10 (
b10 -
b10 +
1&
#140000
0&
#145000
0#
00
b11 .
b11 1
1)
1,
b0 +
b11 !
b11 (
b11 -
1&
#150000
0&
#155000
b0 !
b0 (
b0 -
b1 +
1&
#160000
0&
#165000
b10 +
0%
b1 !
b1 (
b1 -
1&
#170000
0&
#175000
b10 !
b10 (
b10 -
0)
0,
b0 +
1&
#180000
0&
#185000
b1 +
1%
b11 !
b11 (
b11 -
1&
#190000
0&
#195000
b0 !
b0 (
b0 -
b10 +
1&
#200000
0&
#205000
1$
1/
b100 1
b0 .
1)
1,
b0 +
0%
b1 !
b1 (
b1 -
1&
#210000
0&
#215000
b10 !
b10 (
b10 -
b1 +
1&
#220000
0&
#225000
b10 +
1%
b11 !
b11 (
b11 -
1&
#230000
0&
#235000
b0 !
b0 (
b0 -
0)
0,
b0 +
1&
#240000
0&
#245000
b1 +
b1 !
b1 (
b1 -
1&
#250000
0&
#255000
0%
b10 !
b10 (
b10 -
b10 +
1&
#260000
0&
#265000
1#
10
b1 .
b101 1
1)
1,
b0 +
1%
b11 !
b11 (
b11 -
1&
#270000
0&
#275000
b0 !
b0 (
b0 -
b1 +
1&
#280000
0&
#285000
b10 +
b1 !
b1 (
b1 -
1&
#290000
0&
#295000
b10 !
b10 (
b10 -
0)
0,
b0 +
1&
#300000
0&
#305000
b1 +
b11 !
b11 (
b11 -
1&
#310000
0&
#315000
b0 !
b0 (
b0 -
b10 +
1&
#320000
0&
#325000
0$
0/
0"
02
b110 1
b10 .
1)
1,
b0 +
b1 !
b1 (
b1 -
1&
#330000
0&
#335000
b10 !
b10 (
b10 -
b1 +
1&
#340000
0&
#345000
b10 +
0%
b11 !
b11 (
b11 -
1&
#350000
0&
#355000
1%
b0 !
b0 (
b0 -
0)
0,
b0 +
1&
#360000
0&
#365000
b1 +
0%
b1 !
b1 (
b1 -
1&
#370000
0&
#375000
1%
b10 !
b10 (
b10 -
b10 +
1&
#380000
0&
#385000
0#
00
b11 .
b111 1
1)
1,
b0 +
0%
b11 !
b11 (
b11 -
1&
#390000
0&
#395000
1%
b0 !
b0 (
b0 -
b1 +
1&
#400000
0&
#405000
b10 +
0%
b1 !
b1 (
b1 -
1&
#410000
0&
#415000
b10 !
b10 (
b10 -
0)
0,
b0 +
1&
#420000
0&
#425000
b1 +
b11 !
b11 (
b11 -
1&
#430000
0&
#435000
1%
b0 !
b0 (
b0 -
b10 +
1&
#440000
0&
#445000
1$
1/
b1000 1
b0 .
1)
1,
b0 +
0%
b1 !
b1 (
b1 -
1&
#450000
0&
#455000
b10 !
b10 (
b10 -
b1 +
1&
#460000
0&
#465000
b10 +
b11 !
b11 (
b11 -
1&
#470000
0&
#475000
1%
b0 !
b0 (
b0 -
0)
0,
b0 +
1&
#480000
0&
#485000
b1 +
b1 !
b1 (
b1 -
1&
#490000
0&
#495000
0%
b10 !
b10 (
b10 -
b10 +
1&
